<command>
   <code>A0</code>
   <response>
       <value>
          <name>Датчик 0</name>
          <type>int</type>
          <length>2</length>
       </value>
       <value>
          <name>Датчик 1</name>
          <type>int</type>
          <length>2</length>
       </value>
       <value>
          <name>Датчик 2</name>
          <type>int</type>
          <length>2</length>
       </value>
       <value>
          <name>Датчик 3</name>
          <type>int</type>
          <length>2</length>
       </value>
       <value>
          <name>Датчик 4</name>
          <type>int</type>
          <length>2</length>
       </value>
       <value>
          <name>Датчик 5</name>
          <type>int</type>
          <length>2</length>
       </value>
       <value>
          <name>Датчик 6</name>
          <type>int</type>
          <length>2</length>
       </value>
   </response>
</command>
